birdhouse_toolbox/__init__.py
birdhouse_toolbox/exceptions.py
birdhouse_toolbox/settings.py
birdhouse_toolbox/cli/__init__.py
birdhouse_toolbox/cli/main.py
birdhouse_toolbox/cli/options.py
birdhouse_toolbox/cli/analytics/__init__.py
birdhouse_toolbox/cli/analytics/main.py
birdhouse_toolbox/cli/analytics/commands/__init__.py
birdhouse_toolbox/cli/checker/__init__.py
birdhouse_toolbox/cli/checker/main.py
birdhouse_toolbox/cli/checker/commands/__init__.py
birdhouse_toolbox/cli/checker/commands/check.py
birdhouse_toolbox/cli/reports/__init__.py
birdhouse_toolbox/cli/reports/main.py
birdhouse_toolbox/cli/reports/commands/__init__.py
birdhouse_toolbox/cli/reports/commands/create.py
birdhouse_toolbox/cli/wordpress/__init__.py
birdhouse_toolbox/cli/wordpress/add_post.py
birdhouse_toolbox/cli/wordpress/authenticate.py
birdhouse_toolbox/cli/wordpress/get_post.py
birdhouse_toolbox/cli/wordpress/get_posts.py
birdhouse_toolbox/cli/wordpress/main.py
birdhouse_toolbox/cli/wordpress/commands/__init__.py
birdhouse_toolbox/cli/wordpress/commands/add_post.py
birdhouse_toolbox/cli/wordpress/commands/authenticate.py
birdhouse_toolbox/cli/wordpress/commands/create_post.py
birdhouse_toolbox/cli/wordpress/commands/get_post.py
birdhouse_toolbox/cli/wordpress/commands/get_posts.py
birdhouse_toolbox/library/__init__.py
birdhouse_toolbox/library/checker.py
birdhouse_toolbox/library/controller.py
birdhouse_toolbox/library/get_dates_for_duration.py
birdhouse_toolbox/library/make_url.py
birdhouse_toolbox/library/read_config.py
birdhouse_toolbox/library/read_file.py
birdhouse_toolbox/library/request.py
birdhouse_toolbox/library/save_config.py
birdhouse_toolbox/library/analytics/__init__.py
birdhouse_toolbox/library/analytics/controller.py
birdhouse_toolbox/library/analytics/commands/__init__.py
birdhouse_toolbox/library/reports/__init__.py
birdhouse_toolbox/library/reports/commands/__init__.py
birdhouse_toolbox/library/reports/commands/create_monthly_report.py
birdhouse_toolbox-3.4.0.dist-info/LICENSE.txt
birdhouse_toolbox-3.4.0.dist-info/METADATA
birdhouse_toolbox-3.4.0.dist-info/WHEEL
birdhouse_toolbox-3.4.0.dist-info/entry_points.txt
birdhouse_toolbox-3.4.0.dist-info/top_level.txt
birdhouse_toolbox-3.4.0.dist-info/RECORD
