Metadata-Version: 2.1
Name: birdhouse-toolbox
Version: 3.4.0
Summary: Command line tools to automate various processes
Home-page: https://www.alexseitsinger.com/packages/python/birdhouse-toolbox
Author: Alex Seitsinger
Author-email: software@alexseitsinger.com
License: BSD 2-Clause License
Project-URL: Documentation, https://www.alexseitsinger.com/packages/python/birdhouse-toolbox
Project-URL: Source, https://github.com/alexseitsinger/birdhouse-toolbox
Project-URL: Tracker, https://github.com/alexseitsinger/birdhouse-toolbox/issues
Platform: UNKNOWN
Classifier: Development Status :: 5 - Production/Stable
Classifier: Environment :: Console
Classifier: Intended Audience :: Information Technology
Classifier: License :: OSI Approved :: BSD License
Classifier: Natural Language :: English
Classifier: Operating System :: OS Independent
Classifier: Programming Language :: Python :: 2
Classifier: Programming Language :: Python :: 3
Classifier: Topic :: Communications
Classifier: Topic :: Internet :: WWW/HTTP :: Site Management
Classifier: Topic :: Text Processing :: Markup :: HTML
Requires-Dist: requests
Requires-Dist: click
Requires-Dist: python-slugify
Requires-Dist: maya
Requires-Dist: google-api-python-client
Requires-Dist: bs4
Requires-Dist: validators
